AUTHORS.rst
HISTORY.rst
MANIFEST.in
README.rst
requirements.txt
requirements_dev.txt
setup.cfg
setup.py
rlog_generator/__init__.py
rlog_generator/cli.py
rlog_generator/rlog_generator.py
rlog_generator/utils.py
rlog_generator/version.py
rlog_generator.egg-info/PKG-INFO
rlog_generator.egg-info/SOURCES.txt
rlog_generator.egg-info/dependency_links.txt
rlog_generator.egg-info/entry_points.txt
rlog_generator.egg-info/not-zip-safe
rlog_generator.egg-info/requires.txt
rlog_generator.egg-info/top_level.txt
tests/__init__.py
tests/test_rlog_generator.py
tests/test_utils.py
tests/conf/patterns/apache_commons.yml
tests/conf/patterns/dns.yml
tests/conf/patterns_empty/.gitkeep
tests/conf/patterns_err/apache_commons.yml
tests/conf/patterns_err/fake.yml