Metadata-Version: 1.2
Name: rlog-generator
Version: 0.2.0
Summary: Generator of random logs for multiple types of technologies
Home-page: https://github.com/WuerthPhoenix/log-generator
Author: Fedele Mantuano
Author-email: mantuano.fedele@gmail.com
Maintainer: Fedele Mantuano
Maintainer-email: mantuano.fedele@gmail.com
License: UNKNOWN
Keywords: log,generator,random
Platform: Linux
Classifier: Intended Audience :: Developers
Classifier: Natural Language :: English
Classifier: Programming Language :: Python :: 3
Classifier: Programming Language :: Python :: 3.6
Classifier: Programming Language :: Python :: 3.7
